odoo/addons/base_user_role/README.rst
odoo/addons/base_user_role/__init__.py
odoo/addons/base_user_role/__manifest__.py
odoo/addons/base_user_role/data/ir_cron.xml
odoo/addons/base_user_role/data/ir_module_category.xml
odoo/addons/base_user_role/i18n/am.po
odoo/addons/base_user_role/i18n/ar.po
odoo/addons/base_user_role/i18n/base_user_role.pot
odoo/addons/base_user_role/i18n/bg.po
odoo/addons/base_user_role/i18n/bs.po
odoo/addons/base_user_role/i18n/ca.po
odoo/addons/base_user_role/i18n/cs.po
odoo/addons/base_user_role/i18n/da.po
odoo/addons/base_user_role/i18n/de.po
odoo/addons/base_user_role/i18n/el_GR.po
odoo/addons/base_user_role/i18n/en_GB.po
odoo/addons/base_user_role/i18n/es.po
odoo/addons/base_user_role/i18n/es_AR.po
odoo/addons/base_user_role/i18n/es_CL.po
odoo/addons/base_user_role/i18n/es_CO.po
odoo/addons/base_user_role/i18n/es_CR.po
odoo/addons/base_user_role/i18n/es_DO.po
odoo/addons/base_user_role/i18n/es_EC.po
odoo/addons/base_user_role/i18n/es_ES.po
odoo/addons/base_user_role/i18n/es_MX.po
odoo/addons/base_user_role/i18n/es_PE.po
odoo/addons/base_user_role/i18n/es_PY.po
odoo/addons/base_user_role/i18n/es_VE.po
odoo/addons/base_user_role/i18n/et.po
odoo/addons/base_user_role/i18n/eu.po
odoo/addons/base_user_role/i18n/fa.po
odoo/addons/base_user_role/i18n/fi.po
odoo/addons/base_user_role/i18n/fr.po
odoo/addons/base_user_role/i18n/fr_CA.po
odoo/addons/base_user_role/i18n/fr_CH.po
odoo/addons/base_user_role/i18n/fr_FR.po
odoo/addons/base_user_role/i18n/gl.po
odoo/addons/base_user_role/i18n/gl_ES.po
odoo/addons/base_user_role/i18n/he.po
odoo/addons/base_user_role/i18n/hr.po
odoo/addons/base_user_role/i18n/hr_HR.po
odoo/addons/base_user_role/i18n/hu.po
odoo/addons/base_user_role/i18n/id.po
odoo/addons/base_user_role/i18n/it.po
odoo/addons/base_user_role/i18n/ja.po
odoo/addons/base_user_role/i18n/ko.po
odoo/addons/base_user_role/i18n/lt.po
odoo/addons/base_user_role/i18n/lt_LT.po
odoo/addons/base_user_role/i18n/lv.po
odoo/addons/base_user_role/i18n/mk.po
odoo_addon_base_user_role-18.0.1.0.5.4.dist-info/METADATA
odoo_addon_base_user_role-18.0.1.0.5.4.dist-info/WHEEL
odoo_addon_base_user_role-18.0.1.0.5.4.dist-info/top_level.txt
odoo_addon_base_user_role-18.0.1.0.5.4.dist-info/RECORD
