Metadata-Version: 2.1
Name: odoo-addon-base_user_role
Version: 18.0.1.0.5.4
Requires-Python: >=3.10
Requires-Dist: odoo==18.0.*
Summary: User roles
Home-page: https://github.com/OCA/server-backend
License: LGPL-3
Author: ABF OSIELL, Odoo Community Association (OCA)
Author-email: support@odoo-community.org
Classifier: Programming Language :: Python
Classifier: Framework :: Odoo
Classifier: Framework :: Odoo :: 18.0
Classifier: License :: OSI Approved :: GNU Lesser General Public License v3 (LGPLv3)
Classifier: Development Status :: 5 - Production/Stable
